setup.py
easyapp/__init__.py
easyapp/db.py
easyapp/log copy.py
easyapp/log2.py
easyapp/main.py
easyapp/main_init.py
easyapp/result.py
easyapp/tools.py
easyapp.egg-info/PKG-INFO
easyapp.egg-info/SOURCES.txt
easyapp.egg-info/dependency_links.txt
easyapp.egg-info/not-zip-safe
easyapp.egg-info/requires.txt
easyapp.egg-info/top_level.txt