Metadata-Version: 1.0
Name: easyapp
Version: 0.1.4
Summary: a smart api framework based on fastapi
Home-page: http://www.app09.com
Author: JackWang
Author-email: perwang@sina.com
License: MIT Licence
Keywords: api,fastapi,easyapp,smart
Platform: UNKNOWN
